pytradingview/__init__.py
pytradingview/__version__.py
pytradingview/core/TVBridge.py
pytradingview/core/TVBridgeObject.py
pytradingview/core/TVChart.py
pytradingview/core/TVCustomSymbolStatus.py
pytradingview/core/TVCustomSymbolStatusAdapter.py
pytradingview/core/TVCustomThemes.py
pytradingview/core/TVEventBus.py
pytradingview/core/TVObject.py
pytradingview/core/TVObjectPool.py
pytradingview/core/TVSubscribeEventsMap.py
pytradingview/core/TVSubscribeManager.py
pytradingview/core/TVSubscription.py
pytradingview/core/TVWatchedValue.py
pytradingview/core/TVWidget.py
pytradingview/core/TVWidgetConfig.py
pytradingview/core/__init__.py
pytradingview/datafeed/BADatafeed.py
pytradingview/datafeed/TVCallbacks.py
pytradingview/datafeed/TVDataStructures.py
pytradingview/datafeed/TVDatafeed.py
pytradingview/datafeed/TVInterfaces.py
pytradingview/datafeed/TVMarks.py
pytradingview/datafeed/TVQuotes.py
pytradingview/datafeed/TVSymbolInfo.py
pytradingview/datafeed/TVTypes.py
pytradingview/datafeed/__init__.py
pytradingview/indicators/__init__.py
pytradingview/indicators/indicator_base.py
pytradingview/indicators/indicator_config.py
pytradingview/indicators/indicator_engine.py
pytradingview/indicators/indicator_registry.py
pytradingview/indicators/engine/__init__.py
pytradingview/indicators/engine/chart_context.py
pytradingview/indicators/engine/config_mixin.py
pytradingview/indicators/engine/drawing_mixin.py
pytradingview/indicators/engine/loader_mixin.py
pytradingview/indicators/engine/manager_mixin.py
pytradingview/indicators/engine/remote_mixin.py
pytradingview/indicators/engine/runtime_mixin.py
pytradingview/indicators/engine/singleton_mixin.py
pytradingview/models/TVExportedData.py
pytradingview/models/TVNews.py
pytradingview/models/TVPane.py
pytradingview/models/TVSeries.py
pytradingview/models/TVStudy.py
pytradingview/models/TVTimeScale.py
pytradingview/models/TVTimezone.py
pytradingview/models/__init__.py
pytradingview/server/__init__.py
pytradingview/server/app.py
pytradingviewlib-1.0.8.dist-info/licenses/LICENSE
pytradingviewlib-1.0.8.dist-info/METADATA
pytradingviewlib-1.0.8.dist-info/WHEEL
pytradingviewlib-1.0.8.dist-info/entry_points.txt
pytradingviewlib-1.0.8.dist-info/top_level.txt
pytradingviewlib-1.0.8.dist-info/RECORD
