Metadata-Version: 2.4
Name: pytradingviewlib
Version: 1.0.8
Summary: A Python client library for TradingView Widget API. ✨Using Python to interact with TradingView📈, just like using JavaScript🚀🎉
Author-email: LFC <1531724247@qq.com>
License: MIT
Project-URL: Homepage, https://github.com/great-bounty/PyTradingView
Project-URL: Documentation, https://pytradingview.readthedocs.io
Project-URL: Repository, https://github.com/great-bounty/PyTradingView
Project-URL: Bug Tracker, https://github.com/great-bounty/pytradingview/issues
Keywords: charting,electron,indicator,javascript,pandas-ta,python,technical-analysis,tradingview,trading,typescript,vue,binance,investing
Classifier: Development Status :: 5 - Production/Stable
Classifier: Intended Audience :: Developers
Classifier: License :: OSI Approved :: MIT License
Classifier: Programming Language :: Python :: 3
Classifier: Programming Language :: Python :: 3.12
Requires-Python: >=3.12
License-File: LICENSE
Requires-Dist: websocket-client>=1.5.1
Requires-Dist: fastapi>=0.100.0
Requires-Dist: uvicorn>=0.23.0
Requires-Dist: pandas>=1.5.0
Requires-Dist: aiohttp>=3.8.0
Requires-Dist: pathlib>=1.0.1
Requires-Dist: pandas-ta>=0.4.71b0
Provides-Extra: dev
Requires-Dist: pytest>=7.0; extra == "dev"
Requires-Dist: pytest-asyncio>=0.21.0; extra == "dev"
Requires-Dist: black>=23.0; extra == "dev"
Requires-Dist: ruff>=0.0.280; extra == "dev"
Requires-Dist: mypy>=1.0; extra == "dev"
Dynamic: license-file
